scikit_ptm_fs/__init__.py
scikit_ptm_fs/utils.py
scikit_ptm_fs/Base/ProblemTransformation.py
scikit_ptm_fs/Base/__init__.py
scikit_ptm_fs/Base/base.py
scikit_ptm_fs/problem_transformation/BR.py
scikit_ptm_fs/problem_transformation/ELA.py
scikit_ptm_fs/problem_transformation/LP.py
scikit_ptm_fs/problem_transformation/PPT.py
scikit_ptm_fs/problem_transformation/PW.py
scikit_ptm_fs/problem_transformation/__init__.py
scikit_ptm_fs-0.12.dist-info/licenses/LICENSE
scikit_ptm_fs-0.12.dist-info/METADATA
scikit_ptm_fs-0.12.dist-info/WHEEL
scikit_ptm_fs-0.12.dist-info/top_level.txt
scikit_ptm_fs-0.12.dist-info/RECORD
